sdpmflut/__init__.py
sdpmflut/__version__.py
sdpmflut/core/__init__.py
sdpmflut/core/airfoils.py
sdpmflut/core/FEmodes.py
sdpmflut/core/flutsol.py
sdpmflut/core/SDPMcalcs.py
sdpmflut/core/SDPMgeometry.py
sdpmflut/kernels/__init__.py
sdpmflut/kernels/sdpminf_unsteadyso.dll
sdpmflut/kernels/sdpminf_unsteadyso.lib
sdpmflut/kernels/sdpminfso.dll
sdpmflut/kernels/sdpminfso.lib
sdpmflut/kernels/sources/sdpminf_unsteadyso.c
sdpmflut/kernels/sources/sdpminfso.c
sdpmflut/py.typed
sdpmflut-0.6.8.dist-info/METADATA
sdpmflut-0.6.8.dist-info/WHEEL
sdpmflut-0.6.8.dist-info/licenses/LICENSE
sdpmflut-0.6.8.dist-info/RECORD
