Metadata-Version: 2.2
Name: sdpmflut
Version: 0.6.8
Summary: Subsonic unsteady Source-and-Doublet Panel Method for aerodynamics & flutter analysis (packaged)
Keywords: flutter,aeroelasticity,SDPM,aerodynamics
Author-Email: Grigorios Dimitriadis <gdimitriadis@uliege.be>, Khader Abueltayef <abueltayef.khader@gmail.com>
License: MIT License
Classifier: Development Status :: 4 - Beta
Classifier: Intended Audience :: Science/Research
Classifier: License :: OSI Approved :: GNU General Public License v3 (GPLv3)
Classifier: Programming Language :: Python :: 3
Classifier: Programming Language :: Python :: 3.10
Classifier: Programming Language :: Python :: 3.11
Classifier: Programming Language :: Python :: 3.12
Classifier: Programming Language :: Python :: 3.13
Classifier: Topic :: Scientific/Engineering :: Physics
Project-URL: Homepage, https://aeroconsult.gr/
Project-URL: Source, https://aeroconsult.gr/sdpmflut-software/
Requires-Python: >=3.10
Requires-Dist: numpy>=1.26
Requires-Dist: scipy>=1.10
Requires-Dist: matplotlib>=3.7
Requires-Dist: rich>=13.8.0
